gsmcodecs/__init__.py
gsmcodecs/charmaps.py
gsmcodecs-1.0.0.dist-info/LICENSE
gsmcodecs-1.0.0.dist-info/METADATA
gsmcodecs-1.0.0.dist-info/WHEEL
gsmcodecs-1.0.0.dist-info/top_level.txt
gsmcodecs-1.0.0.dist-info/RECORD
