Metadata-Version: 2.1
Name: gsmcodecs
Version: 1.0.0
Summary: Python codecs for 3GPP TS 23.038
Author-email: Nathan Fraser <ndf-zz@6-v.org>
License: MIT
Project-URL: homepage, https://github.com/ndf-zz/gsmcodecs
Keywords: 3GPP,TS,23.038,codec,GSM,SMS,PDU
Classifier: Development Status :: 3 - Alpha
Classifier: Topic :: Other/Nonlisted Topic
Classifier: Intended Audience :: Developers
Classifier: License :: OSI Approved :: MIT License
Classifier: Operating System :: OS Independent
Classifier: Programming Language :: Python :: 3
Classifier: Topic :: Communications :: Telephony
Requires-Python: >=3.9
License-File: LICENSE
